textverified_async/__init__.py
textverified_async/api.py
textverified_async/models.py
textverified_async-0.0.2.dist-info/METADATA
textverified_async-0.0.2.dist-info/WHEEL
textverified_async-0.0.2.dist-info/top_level.txt
textverified_async-0.0.2.dist-info/RECORD
