Metadata-Version: 2.4
Name: textverified_async
Version: 0.0.2
Summary: A simple asynchronous Python API client for working with the Textverified REST API
Author: keynet
Author-email: viktorplay377@gmail.com
Project-URL: GitHub, https://github.com/Keynet123
Keywords: textverified api client async asynchronous
Classifier: Programming Language :: Python :: 3.10
Classifier: License :: OSI Approved :: MIT License
Classifier: Operating System :: OS Independent
Requires-Python: >=3.9
Requires-Dist: aiohttp
Requires-Dist: pydantic
Dynamic: author
Dynamic: author-email
Dynamic: classifier
Dynamic: description
Dynamic: description-content-type
Dynamic: keywords
Dynamic: project-url
Dynamic: requires-dist
Dynamic: requires-python
Dynamic: summary
